mffpy/__init__.py
mffpy/bin_files.py
mffpy/bin_writer.py
mffpy/cached_property.py
mffpy/devices.py
mffpy/dict2xml.py
mffpy/epoch.py
mffpy/mffdir.py
mffpy/raw_bin_files.py
mffpy/reader.py
mffpy/version.py
mffpy/writer.py
mffpy/xml_files.py
mffpy/zipfile.py
mffpy/header_block/__init__.py
mffpy/header_block/header_block.py
mffpy/header_block/helpers.py
mffpy/header_block/optional_header_block.py
mffpy/resources/coordinates/Geodesic Head Web 130 1.0.xml
mffpy/resources/coordinates/Geodesic Head Web 280 1.0.xml
mffpy/resources/coordinates/Geodesic Sensor Net 128 2.1.xml
mffpy/resources/coordinates/Geodesic Sensor Net 256 2.1.xml
mffpy/resources/coordinates/Geodesic Sensor Net 64 2.0.xml
mffpy/resources/coordinates/HydroCel GSN 128 1.0.xml
mffpy/resources/coordinates/HydroCel GSN 256 1.0.xml
mffpy/resources/coordinates/HydroCel GSN 32 1.0.xml
mffpy/resources/coordinates/HydroCel GSN 64 1.0.xml
mffpy/resources/coordinates/MicroCel GSN 100 128 1.0.xml
mffpy/resources/coordinates/MicroCel GSN 100 256 1.0.xml
mffpy/resources/coordinates/MicroCel GSN 100 32 1.0.xml
mffpy/resources/coordinates/MicroCel GSN 100 64 1.0.xml
mffpy/resources/coordinates/Standard 10-20 (19 ch).xml
mffpy/resources/sensorLayout/Amp Sample.xml
mffpy/resources/sensorLayout/Geodesic Head Web 130 1.0.xml
mffpy/resources/sensorLayout/Geodesic Head Web 280 1.0.xml
mffpy/resources/sensorLayout/Geodesic Sensor Net 128 2.1.xml
mffpy/resources/sensorLayout/Geodesic Sensor Net 256 2.1.xml
mffpy/resources/sensorLayout/Geodesic Sensor Net 64 2.0.xml
mffpy/resources/sensorLayout/HydroCel GSN 128 1.0.xml
mffpy/resources/sensorLayout/HydroCel GSN 256 1.0.xml
mffpy/resources/sensorLayout/HydroCel GSN 32 1.0.xml
mffpy/resources/sensorLayout/HydroCel GSN 64 1.0.xml
mffpy/resources/sensorLayout/MicroCel GSN 100 128 1.0.xml
mffpy/resources/sensorLayout/MicroCel GSN 100 256 1.0.xml
mffpy/resources/sensorLayout/MicroCel GSN 100 32 1.0.xml
mffpy/resources/sensorLayout/MicroCel GSN 100 64 1.0.xml
mffpy-0.10.0.dist-info/LICENSE
mffpy-0.10.0.dist-info/METADATA
mffpy-0.10.0.dist-info/WHEEL
mffpy-0.10.0.dist-info/top_level.txt
mffpy-0.10.0.dist-info/RECORD
