Metadata-Version: 2.1
Name: mffpy
Version: 0.10.0
Summary: Reader and Writer for Philips' MFF file format.
Home-page: UNKNOWN
Author: Justus Schwabedal, Wayne Manselle
Author-email: jschwabedal@belco.tech, wayne.manselle@belco.tech
Maintainer: Evan Hathaway
Maintainer-email: evan.hathaway@belco.tech
License: UNKNOWN
Platform: UNKNOWN
Classifier: Programming Language :: Python :: 3
Classifier: License :: OSI Approved :: Apache Software License
Classifier: Operating System :: OS Independent
Requires-Python: >=3.6
License-File: LICENSE
Requires-Dist: lxml (>=4.8.0)
Requires-Dist: pytz (>=2019.2)
Requires-Dist: numpy (>=1.15.1)
Requires-Dist: Deprecated (>=1.2.12)
